{
  "db_name": "PostgreSQL",
  "query": "SELECT c.channel_type, c.external_id, c.external_chat_id\n                                    FROM channels c\n                                    JOIN conversation_members cm ON c.user_id = cm.user_id\n                                    WHERE cm.conversation_id = $1 AND c.channel_type = ANY($2::text[])",
  "describe": {
    "columns": [
      {
        "ordinal": 0,
        "name": "channel_type",
        "type_info": "Text"
      },
      {
        "ordinal": 1,
        "name": "external_id",
        "type_info": "Text"
      },
      {
        "ordinal": 2,
        "name": "external_chat_id",
        "type_info": "Text"
      }
    ],
    "parameters": {
      "Left": [
        "Uuid",
        "TextArray"
      ]
    },
    "nullable": [
      false,
      false,
      false
    ]
  },
  "hash": "fa5b56c53272b744957eda4a02b30ffbf07c7f35cc33b9669fb6c67eb253b185"
}
